libixrub/How.py
libixrub/Servers.py
libixrub/__init__.py
libixrub/client.py
libixrub/okb.py
libixrub-0.0.1.dist-info/LICENCE
libixrub-0.0.1.dist-info/METADATA
libixrub-0.0.1.dist-info/WHEEL
libixrub-0.0.1.dist-info/top_level.txt
libixrub-0.0.1.dist-info/RECORD
